[
    {
        "検索key": "NKインターナショナル株式会社川崎港コンテナターミナル40HC",
        "荷主リフトオフ": 1000.0,
        "荷主リフトオン": 2000.0,
        "荷主保管1日": 3000.0,
        "下払リフトオフ": 4000.0,
        "下払リフトオン": 5000.0,
        "下払保管1日": 6000.0,
        "荷主保管課税": false,
        "下払保管課税": false
    },
    {
        "検索key": "NKインターナショナル株式会社川崎港コンテナターミナル40RE",
        "荷主リフトオフ": null,
        "荷主リフトオン": null,
        "荷主保管1日": null,
        "下払リフトオフ": null,
        "下払リフトオン": null,
        "下払保管1日": null,
        "荷主保管課税": false,
        "下払保管課税": false
    },
    {
        "検索key": "伊藤忠ロジスティクス株式会社シバカイ",
        "荷主リフトオフ": null,
        "荷主リフトオン": null,
        "荷主保管1日": null,
        "下払リフトオフ": null,
        "下払リフトオン": null,
        "下払保管1日": null,
        "荷主保管課税": false,
        "下払保管課税": false
    },
    {
        "検索key": "NKインターナショナル株式会社川崎港コンテナターミナル40",
        "荷主リフトオフ": 7000.0,
        "荷主リフトオン": 7000.0,
        "荷主保管1日": 2500.0,
        "下払リフトオフ": 6000.0,
        "下払リフトオン": 6000.0,
        "下払保管1日": 1300.0,
        "荷主保管課税": false,
        "下払保管課税": false
    },
    {
        "検索key": "株式会社後藤回漕店　東京南本牧日新20TNK",
        "荷主リフトオフ": 6000.0,
        "荷主リフトオン": 6000.0,
        "荷主保管1日": 2000.0,
        "下払リフトオフ": 3500.0,
        "下払リフトオン": 3500.0,
        "下払保管1日": 500.0,
        "荷主保管課税": false,
        "下払保管課税": false
    },
    {
        "検索key": "㈱近鉄エクスプレス　輸入川崎港コンテナターミナル40",
        "荷主リフトオフ": 9.0,
        "荷主リフトオン": 9.0,
        "荷主保管1日": 9.0,
        "下払リフトオフ": 9.0,
        "下払リフトオン": 9.0,
        "下払保管1日": 9.0,
        "荷主保管課税": true,
        "下払保管課税": true
    },
    {
        "検索key": "株式会社後藤回漕店　東京株式会社上組20TNK",
        "荷主リフトオフ": 11000.0,
        "荷主リフトオン": 11000.0,
        "荷主保管1日": 2000.0,
        "下払リフトオフ": 10000.0,
        "下払リフトオン": 10000.0,
        "下払保管1日": 1000.0,
        "荷主保管課税": false,
        "下払保管課税": false
    },
    {
        "検索key": "NKインターナショナル株式会社川崎港コンテナターミナル20",
        "荷主リフトオフ": 1000.0,
        "荷主リフトオン": 2000.0,
        "荷主保管1日": 0.0,
        "下払リフトオフ": 3000.0,
        "下払リフトオン": 4000.0,
        "下払保管1日": 0.0,
        "荷主保管課税": false,
        "下払保管課税": false
    },
    {
        "検索key": "㈱近鉄エクスプレス　輸入TEST_CNT340",
        "荷主リフトオフ": 12.0,
        "荷主リフトオン": 23.0,
        "荷主保管1日": 34.0,
        "下払リフトオフ": 45.0,
        "下払リフトオン": 56.0,
        "下払保管1日": 67.0,
        "荷主保管課税": false,
        "下払保管課税": false
    },
    {
        "検索key": "㈱近鉄エクスプレス　輸入川崎港コンテナターミナル",
        "荷主リフトオフ": 9.0,
        "荷主リフトオン": 9.0,
        "荷主保管1日": 9.0,
        "下払リフトオフ": 9.0,
        "下払リフトオン": 9.0,
        "下払保管1日": 9.0,
        "荷主保管課税": true,
        "下払保管課税": true
    },
    {
        "検索key": "㈱近鉄エクスプレス　輸入ABC40",
        "荷主リフトオフ": 1.0,
        "荷主リフトオン": 2.0,
        "荷主保管1日": 3.0,
        "下払リフトオフ": 1.0,
        "下払リフトオン": 2.0,
        "下払保管1日": 3.0,
        "荷主保管課税": true,
        "下払保管課税": true
    },
    {
        "検索key": "㈱近鉄エクスプレス　輸入保管配達場所B40",
        "荷主リフトオフ": 10.0,
        "荷主リフトオン": 20.0,
        "荷主保管1日": 30.0,
        "下払リフトオフ": 40.0,
        "下払リフトオン": 50.0,
        "下払保管1日": 60.0,
        "荷主保管課税": true,
        "下払保管課税": true
    },
    {
        "検索key": "㈱近鉄エクスプレス　輸入株式会社アルプス物流40",
        "荷主リフトオフ": 0.0,
        "荷主リフトオン": 0.0,
        "荷主保管1日": 0.0,
        "下払リフトオフ": 0.0,
        "下払リフトオン": 0.0,
        "下払保管1日": 0.0,
        "荷主保管課税": true,
        "下払保管課税": true
    },
    {
        "検索key": "日新運輸株式会社エムズICD40",
        "荷主リフトオフ": 5000.0,
        "荷主リフトオン": 5000.0,
        "荷主保管1日": 1500.0,
        "下払リフトオフ": 5000.0,
        "下払リフトオン": 5000.0,
        "下払保管1日": 1500.0,
        "荷主保管課税": true,
        "下払保管課税": true
    }
]